{
 "attach_print": 0,
 "channel": "System Notification",
 "creation": "2025-01-23 12:25:18.281644",
 "days_in_advance": 0,
 "docstatus": 0,
 "doctype": "Notification",
 "document_type": "Library Member",
 "enabled": 1,
 "event": "Save",
 "idx": 0,
 "is_standard": 1,
 "message": "<p>A new member {doc.first_name} is created in library management system</p>\n",
 "message_type": "Markdown",
 "modified": "2025-01-24 21:55:03.066596",
 "modified_by": "Administrator",
 "module": "Library App",
 "name": "new_member_notification",
 "owner": "Administrator",
 "recipients": [
  {
   "receiver_by_document_field": "owner"
  }
 ],
 "send_system_notification": 0,
 "send_to_all_assignees": 0,
 "subject": "New Member added!"
}